[
  {
    "id": "6805702c-f3c0-4af4-82b7-21cc427dd125",
    "title": "(社員共有用)評価制度について",
    "description": "",
    "fileName": "6805702c-f3c0-4af4-82b7-21cc427dd125.pdf",
    "originalFileName": "(社員共有用)評価制度について.pdf",
    "filePath": "6805702c-f3c0-4af4-82b7-21cc427dd125.pdf",
    "fileSize": 2377698,
    "mimeType": "application/pdf",
    "extractedText": "スピードリンクジャパンの評価制度\n\n目次\n資料の見やすさや内容の分かりやすさを追及するため\n資料の構成や記載の仕方を一部修正しております。\n目次を一度確認してから、欲しい情報を探しにいってください࢜\n\n2025/03/31　評価運営（里村）\n\nSLG（スピードリンク・グレード）\n●概要\n○ミッションの概要\n○グレードの概要\n○報酬について（給与の内訳・グレード手当・昇給の流れ）\n●各グレードの詳細\n○グレード一覧（条件とそれぞれのミッション）\n○各グレードのミッション詳細\n●SLGの運用について\n○評価サイクル（評価タイミング・評価フロー）\n○昇進・降格に関して\n○その他、制度設計における重要事項\n\n評価制度の全体像\n\n弊社の評価制度は、【ミッション遂行】を軸とした仕組みです。\n各メンバーは、自身のグレードに応じたミッションを遂行し、\nその結果に基づいて評価・昇進が決定されます。\n\n評価の観点\n1. ミッション達成度\n2. 行動指針の体現\n3. チームへの貢献\n4. 継続的な学習・成長",
    "tags": [],
    "uploadedBy": "102943004485611536944",
    "uploadedAt": "2025-08-19T13:58:57.277Z",
    "version": 1,
    "isActive": true,
    "updatedAt": "2025-08-19T14:27:58.280Z"
  },
  {
    "id": "5e2d37b5-3bd6-4f6d-bb8a-0df671dcb361",
    "title": "21期UNIT-RUN_説明資料",
    "description": "",
    "fileName": "5e2d37b5-3bd6-4f6d-bb8a-0df671dcb361.pdf",
    "originalFileName": "21期UNIT-RUN_説明資料.pdf",
    "filePath": "5e2d37b5-3bd6-4f6d-bb8a-0df671dcb361.pdf",
    "fileSize": 1065719,
    "mimeType": "application/pdf",
    "extractedText": "21期UNIT-RUN説明資料\n\nユニット制度について\nスピードリンクジャパンでは、メンバーがより効果的に協力し、\n目標を達成するためのユニット制度を導入しています。\n\nユニットの目的\n- チームワークの向上\n- 個人のスキル向上\n- 会社全体の成長促進\n- 効率的な業務運営\n\n各ユニットの構成\n- リーダー1名\n- メンバー3-5名\n- サポートスタッフ\n\n運営方針\n月次での成果確認と改善を継続的に実施し、\n四半期ごとの大きな振り返りを通じて\nより良いチーム作りを目指します。",
    "tags": [],
    "uploadedBy": "102943004485611536944",
    "uploadedAt": "2025-08-19T13:59:07.193Z",
    "version": 1,
    "isActive": true
  }
]